sqterm/__init__.py
sqterm/__main__.py
sqterm/commands/__init__.py
sqterm/commands/changedb.py
sqterm/commands/clearscreen.py
sqterm/commands/dbstats.py
sqterm/commands/dir.py
sqterm/commands/exit.py
sqterm/commands/exportcsv.py
sqterm/commands/help.py
sqterm/commands/importcsv.py
sqterm/commands/integritycheck.py
sqterm/commands/showdata.py
sqterm/commands/showspecificdata.py
sqterm/core/__init__.py
sqterm/core/connector.py
sqterm/core/executer.py
sqterm/core/inputs.py
sqterm/core/main.py
sqterm/extras/__init__.py
sqterm/extras/art.py
sqterm/extras/autocomplete.py
sqterm/extras/colors.py
sqterm/extras/loading.py
sqterm-1.3.4.dist-info/licenses/LICENSE
sqterm-1.3.4.dist-info/METADATA
sqterm-1.3.4.dist-info/WHEEL
sqterm-1.3.4.dist-info/entry_points.txt
sqterm-1.3.4.dist-info/top_level.txt
sqterm-1.3.4.dist-info/RECORD
