Metadata-Version: 2.4
Name: sqterm
Version: 1.3.4
Summary: Terminal-based SQLite manager
Author: Gbot
License: MIT License
Requires-Python: >=3.9
License-File: LICENSE
Requires-Dist: tabulate
Requires-Dist: petl
Requires-Dist: psutil
Requires-Dist: sqlalchemy
Dynamic: license-file
